Optionchain/__init__.py
aliceblueindia-0.1.dist-info/LICENSE.txt
aliceblueindia-0.1.dist-info/METADATA
aliceblueindia-0.1.dist-info/WHEEL
aliceblueindia-0.1.dist-info/top_level.txt
aliceblueindia-0.1.dist-info/RECORD
